Workbook

Sheet Branch1
A1: Account | B1: Jan | C1: Feb | D1: Mar | E1: Apr | F1: May | G1: Jun | H1: Jul | I1: Aug | J1: Sep | K1: Oct | L1: Nov | M1: Dec
A2: Revenue | B2: 175166 | C2: 192926 | D2: 166756 | E2: 164357 | F2: 172069 | G2: 196059 | H2: 100270 | I2: 101651 | J2: 199162 | K2: 151028 | L2: 145238 | M2: 109098
A3: COGS | B3: 73569 | C3: 106109 | D3: 100053 | E3: 70673 | F3: 77431 | G3: 103911 | H3: 46124 | I3: 42693 | J3: 87631 | K3: 74003 | L3: 81333 | M3: 64367
A4: Gross Profit | B4: =B2-B3 -> 101597 | C4: =C2-C3 -> 86817 | D4: =D2-D3 -> 66703 | E4: =E2-E3 -> 93684 | F4: =F2-F3 -> 94638 | G4: =G2-G3 -> 92148 | H4: =H2-H3 -> 54146 | I4: =I2-I3 -> 58958 | ... M4: =M2-M3 -> 44731
A5: Salaries | B5: 4949 | C5: 9776 | D5: 4613 | E5: 5763 | F5: 2996 | G5: 4555 | H5: 4752 | I5: 11418 | J5: 7196 | K5: 2513 | L5: 2184 | M5: 4221
A6: Rent | B6: 9445 | C6: 9026 | D6: 1054 | E6: 8368 | F6: 8197 | G6: 6954 | H6: 9381 | I6: 3111 | J6: 6880 | K6: 6611 | L6: 5890 | M6: 6256
A7: Utilities | B7: 4524 | C7: 6008 | D7: 10583 | E7: 3134 | F7: 2507 | G7: 5202 | H7: 4236 | I7: 6138 | J7: 2972 | K7: 8189 | L7: 6258 | M7: 1650
A8: Marketing | B8: 2036 | C8: 8522 | D8: 8020 | E8: 11301 | F8: 10210 | G8: 3758 | H8: 5166 | I8: 11271 | J8: 5658 | K8: 8209 | L8: 6696 | M8: 6276
A9: Insurance | B9: 10722 | C9: 10983 | D9: 10552 | E9: 4979 | F9: 8023 | G9: 1342 | H9: 2664 | I9: 3968 | J9: 6769 | K9: 2350 | L9: 5901 | M9: 10578
A10: Depreciation | B10: 5950 | C10: 8444 | D10: 5479 | E10: 3862 | F10: 11877 | G10: 1470 | H10: 3367 | I10: 7234 | J10: 7787 | K10: 1513 | L10: 7320 | M10: 6747
A11: Travel | B11: 11646 | C11: 7238 | D11: 7876 | E11: 9144 | F11: 9111 | G11: 3082 | H11: 5432 | I11: 10902 | J11: 7078 | K11: 8235 | L11: 7715 | M11: 8111
A12: Supplies | B12: 1284 | C12: 8691 | D12: 9859 | E12: 11609 | F12: 9552 | G12: 10540 | H12: 4273 | I12: 9442 | J12: 4239 | K12: 1543 | L12: 4008 | M12: 9610
A13: Maintenance | B13: 10664 | C13: 1863 | D13: 4538 | E13: 6158 | F13: 2480 | G13: 1873 | H13: 3006 | I13: 7362 | J13: 4105 | K13: 11871 | L13: 4791 | M13: 10266
A14: Total Opex | B14: =SUM(B5:B13) -> 61220 | C14: =SUM(C5:C13) -> 70551 | D14: =SUM(D5:D13) -> 62574 | E14: =SUM(E5:E13) -> 64318 | F14: =SUM(F5:F13) -> 64953 | G14: =SUM(G5:G13) -> 38776 | H14: =SUM(H5:H13) -> 42277 | I14: =SUM(I5:I13) -> 70846 | ... M14: =SUM(M5:M13) -> 63715
A15: Operating Profit | B15: =B4-B14 -> 40377 | C15: =C4-C14 -> 16266 | D15: =D4-D14 -> 4129 | E15: =E4-E14 -> 29366 | F15: =F4-F14 -> 29685 | G15: =G4-G14 -> 53372 | H15: =H4-H14 -> 11869 | I15: =I4-I14 -> -11888 | ... M15: =M4-M14 -> -18984
A16: Margin | B16: =B15/B2 -> 0.23050706 | C16: =C15/C2 -> 0.08431212 | D16: =D15/D2 -> 0.024760728 | E16: =E15/E2 -> 0.17867204 | F16: =F15/F2 -> 0.172518 | G16: =G15/G2 -> 0.27222418 | H16: =H15/H2 -> 0.1183704 | I16: =I15/I2 -> -0.11694917 | ... M16: =M15/M2 -> -0.17400869

Sheet Branch2
A1: Account | B1: Jan | C1: Feb | D1: Mar | E1: Apr | F1: May | G1: Jun | H1: Jul | I1: Aug | J1: Sep | K1: Oct | L1: Nov | M1: Dec
A2: Revenue | B2: 190464 | C2: 129721 | D2: 145218 | E2: 108436 | F2: 88774 | G2: 195555 | H2: 101270 | I2: 89027 | J2: 153709 | K2: 169223 | L2: 147479 | M2: 145714
A3: COGS | B3: 114278 | C3: 75238 | D3: 69704 | E3: 48796 | F3: 44387 | G3: 82133 | H3: 54685 | I3: 48964 | J3: 66094 | K3: 76150 | L3: 63415 | M3: 80142
A4: Gross Profit | B4: =B2-B3 -> 76186 | C4: =C2-C3 -> 54483 | D4: =D2-D3 -> 75514 | E4: =E2-E3 -> 59640 | F4: =F2-F3 -> 44387 | G4: =G2-G3 -> 113422 | H4: =H2-H3 -> 46585 | I4: =I2-I3 -> 40063 | ... M4: =M2-M3 -> 65572
A5: Salaries | B5: 4378 | C5: 5561 | D5: 7448 | E5: 9286 | F5: 10811 | G5: 3901 | H5: 9092 | I5: 4624 | J5: 4864 | K5: 1139 | L5: 5013 | M5: 9322
A6: Rent | B6: 6604 | C6: 8972 | D6: 1191 | E6: 4220 | F6: 3539 | G6: 1277 | H6: 8911 | I6: 10364 | J6: 7574 | K6: 9782 | L6: 11932 | M6: 1307
A7: Utilities | B7: 7638 | C7: 11977 | D7: 7671 | E7: 6677 | F7: 3306 | G7: 9689 | H7: 10569 | I7: 10402 | J7: 10184 | K7: 6090 | L7: 2253 | M7: 5449
A8: Marketing | B8: 4755 | C8: 4432 | D8: 2986 | E8: 7161 | F8: 5405 | G8: 2160 | H8: 8402 | I8: 9379 | J8: 1177 | K8: 9000 | L8: 7226 | M8: 10071
A9: Insurance | B9: 6699 | C9: 7783 | D9: 6811 | E9: 4670 | F9: 4784 | G9: 5466 | H9: 10563 | I9: 9146 | J9: 6855 | K9: 7405 | L9: 10318 | M9: 4335
A10: Depreciation | B10: 7467 | C10: 8687 | D10: 9782 | E10: 7988 | F10: 7907 | G10: 4793 | H10: 2174 | I10: 7066 | J10: 11862 | K10: 11896 | L10: 1938 | M10: 1096
A11: Travel | B11: 10005 | C11: 5669 | D11: 3625 | E11: 1959 | F11: 6197 | G11: 10073 | H11: 4040 | I11: 10261 | J11: 11369 | K11: 6671 | L11: 9187 | M11: 8750
A12: Supplies | B12: 6210 | C12: 3312 | D12: 8303 | E12: 1611 | F12: 2871 | G12: 5793 | H12: 8547 | I12: 2523 | J12: 8036 | K12: 8905 | L12: 8577 | M12: 9578
A13: Maintenance | B13: 8627 | C13: 10375 | D13: 9120 | E13: 11232 | F13: 8792 | G13: 5584 | H13: 2127 | I13: 1608 | J13: 11624 | K13: 6096 | L13: 7342 | M13: 9518
A14: Total Opex | B14: =SUM(B5:B13) -> 62383 | C14: =SUM(C5:C12) -> 56393 | D14: =SUM(D5:D13) -> 56937 | E14: =SUM(E5:E13) -> 54804 | F14: =SUM(F5:F13) -> 53612 | G14: =SUM(G5:G13) -> 48736 | H14: =SUM(H5:H13) -> 64425 | I14: =SUM(I5:I13) -> 65373 | J14: =SUM(J5:J13) -> 73545 | K14: =SUM(K5:K13) -> 66984 | ... M14: =SUM(M5:M13) -> 59426
A15: Operating Profit | B15: =B4-B14 -> 13803 | C15: =C4-C14 -> -1910 | D15: =D4-D14 -> 18577 | E15: =E4-E14 -> 4836 | F15: =F4-F14 -> -9225 | G15: =G4-G14 -> 64686 | H15: =H4-H14 -> -17840 | I15: =I4-I14 -> -25310 | ... M15: =M4-M14 -> 6146
A16: Margin | B16: =B15/B2 -> 0.072470388 | C16: =C15/C2 -> -0.014723907 | D16: =D15/D2 -> 0.12792491 | E16: =E15/E2 -> 0.044597735 | F16: =F15/F2 -> -0.10391556 | G16: =G15/G2 -> 0.33078162 | H16: =H15/H2 -> -0.17616273 | I16: =I15/I2 -> -0.28429578 | ... M16: =M15/M2 -> 0.042178514

Sheet Branch3
A1: Account | B1: Jan | C1: Feb | D1: Mar | E1: Apr | F1: May | G1: Jun | H1: Jul | I1: Aug | J1: Sep | K1: Oct | L1: Nov | M1: Dec
A2: Revenue | B2: 120094 | C2: 168165 | D2: 175659 | E2: 159121 | F2: 102704 | G2: 142915 | H2: 0 | I2: 159863 | J2: 195337 | K2: 117945 | L2: 146719 | M2: 106740
A3: COGS | B3: 61247 | C3: 75674 | D3: 101882 | E3: 90698 | F3: 54433 | G3: 71457 | H3: 0 | I3: 86326 | J3: 107435 | K3: 56613 | L3: 86564 | M3: 50167
A4: Gross Profit | B4: =B2-B3 -> 58847 | C4: =C2-C3 -> 92491 | D4: =D2-D3 -> 73777 | E4: =E2-E3 -> 68423 | F4: =F2-F3 -> 48271 | G4: =G2-G3 -> 71458 | H4: =H2-H3 -> 0 | I4: =I2-I3 -> 73537 | ... M4: =M2-M3 -> 56573
A5: Salaries | B5: 11412 | C5: 9684 | D5: 5443 | E5: 8806 | F5: 3152 | G5: 10639 | H5: 7672 | I5: 8507 | J5: 3228 | K5: 2831 | L5: 1552 | M5: 1739
A6: Rent | B6: 4133 | C6: 4461 | D6: 9937 | E6: 7650 | F6: 10662 | G6: 6247 | H6: 8002 | I6: 2643 | J6: 7323 | K6: 2168 | L6: 2977 | M6: 10346
A7: Utilities | B7: 4987 | C7: 11138 | D7: 7232 | E7: 11128 | F7: 2901 | G7: 4153 | H7: 6851 | I7: 9020 | J7: 4007 | K7: 5756 | L7: 4593 | M7: 6229
A8: Marketing | B8: 5772 | C8: 10666 | D8: 8643 | E8: 3783 | F8: 4798 | G8: 4099 | H8: 7575 | I8: 9457 | J8: 5389 | K8: 2480 | L8: 10958 | M8: 10176
A9: Insurance | B9: 4165 | C9: 11985 | D9: 10940 | E9: 5224 | F9: 6213 | G9: 2313 | H9: 7325 | I9: 3910 | J9: 3302 | K9: 8846 | L9: 10164 | M9: 5365
A10: Depreciation | B10: 7244 | C10: 8531 | D10: 10769 | E10: 11500 | F10: 1031 | G10: 10569 | H10: 2839 | I10: 3038 | J10: 4837 | K10: 4927 | L10: 4644 | M10: 4015
A11: Travel | B11: 1828 | C11: 10696 | D11: 8234 | E11: 3063 | F11: 5636 | G11: 7981 | H11: 1007 | I11: 10626 | J11: 11794 | K11: 11816 | L11: 10643 | M11: 10816
A12: Supplies | B12: 1925 | C12: 11885 | D12: 2980 | E12: 1570 | F12: 10075 | G12: 7405 | H12: 11605 | I12: 10451 | J12: 8106 | K12: 3868 | L12: 4540 | M12: 2994
A13: Maintenance | B13: 10975 | C13: 10969 | D13: 7247 | E13: 9991 | F13: 1682 | G13: 1325 | H13: 7463 | I13: 9183 | J13: 9248 | K13: 7194 | L13: 5619 | M13: 3071
A14: Total Opex | B14: =SUM(B5:B13) -> 52441 | C14: =SUM(C5:C13) -> 90015 | D14: =SUM(D5:D13) -> 71425 | E14: =SUM(E5:E13) -> 62715 | F14: =SUM(F5:F13) -> 46150 | G14: =SUM(G5:G13) -> 54731 | H14: =SUM(H5:H13) -> 60339 | I14: =SUM(I5:I13) -> 66835 | ... M14: =SUM(M5:M13) -> 54751
A15: Operating Profit | B15: =B4-B14 -> 6406 | C15: =C4-C14 -> 2476 | D15: =D4-D14 -> 2352 | E15: =E4-E14 -> 5708 | F15: =F4-F14 -> 2121 | G15: =G4-G14 -> 16727 | H15: =H4-H14 -> -60339 | I15: =I4-I14 -> 6702 | ... M15: =M4-M14 -> 1822
A16: Margin | B16: =B15/B2 -> 0.053341549 | C16: =C15/C2 -> 0.014723635 | D16: =D15/D2 -> 0.013389579 | E16: =E15/E2 -> 0.035872072 | F16: =F15/F2 -> 0.020651581 | G16: =G15/G2 -> 0.1170416 | H16: =H15/H2 -> #DIV/0! | I16: =I15/I2 -> 0.041923397 | ... M16: =M15/M2 -> 0.017069515

Sheet Branch4
A1: Account | B1: Jan | C1: Feb | D1: Mar | E1: Apr | F1: May | G1: Jun | H1: Jul | I1: Aug | J1: Sep | K1: Oct | L1: Nov | M1: Dec
A2: Revenue | B2: 86628 | C2: 193369 | D2: 185954 | E2: 192390 | F2: 84624 | G2: 147667 | H2: 155630 | I2: 126214 | J2: 153647 | K2: 155375 | L2: 91928 | M2: 111675
A3: COGS | B3: 45912 | C3: 94750 | D3: 94836 | E3: 107738 | F3: 38080 | G3: 72356 | H3: 80927 | I3: 53009 | J3: 92188 | K3: 93225 | L3: 50560 | M3: 59187
A4: Gross Profit | B4: =B2-B3 -> 40716 | C4: =C2-C3 -> 98619 | D4: =D2-D3 -> 91118 | E4: =E2-E3 -> 84652 | F4: =F2-F3 -> 46544 | G4: =G2-G3 -> 75311 | H4: =H2-H3 -> 74703 | I4: =I2-I3 -> 73205 | ... M4: =M2-M3 -> 52488
A5: Salaries | B5: 3374 | C5: 9855 | D5: 4731 | E5: 9730 | F5: 10723 | G5: 5305 | H5: 8360 | I5: 5963 | J5: 1834 | K5: 7150 | L5: 9282 | M5: 5668
A6: Rent | B6: 8704 | C6: 1255 | D6: 8606 | E6: 8581 | F6: 2215 | G6: 4902 | H6: 9495 | I6: 5693 | J6: 5953 | K6: 9999 | L6: 8345 | M6: 4655
A7: Utilities | B7: 11582 | C7: 5046 | D7: 11727 | E7: 10735 | F7: 2638 | G7: 6358 | H7: 9757 | I7: 9616 | J7: 1558 | K7: 2956 | L7: 10516 | M7: 1141
A8: Marketing | B8: 5586 | C8: 9911 | D8: 8464 | E8: 4503 | F8: 2098 | G8: 6000 | H8: 6039 | I8: 3097 | J8: 11840 | K8: 2306 | L8: 1938 | M8: 1633
A9: Insurance | B9: 11833 | C9: 4019 | D9: 5242 | E9: 8237 | F9: 10481 | G9: 11655 | H9: 5337 | I9: 2061 | J9: 10908 | K9: 2780 | L9: 9031 | M9: 8640
A10: Depreciation | B10: 5182 | C10: 10838 | D10: 7177 | E10: 7288 | F10: 2809 | G10: 4869 | H10: 1791 | I10: 6580 | J10: 3602 | K10: 6350 | L10: 1668 | M10: 9428
A11: Travel | B11: 7690 | C11: 5175 | D11: 4956 | E11: 8884 | F11: 2494 | G11: 4907 | H11: 10132 | I11: 11164 | J11: 8008 | K11: 1376 | L11: 3131 | M11: 4202
A12: Supplies | B12: 7241 | C12: 5453 | D12: 11103 | E12: 3503 | F12: 8798 | G12: 4181 | H12: 7162 | I12: 11230 | J12: 8933 | K12: 8094 | L12: 8352 | M12: 8461
A13: Maintenance | B13: 5956 | C13: 2182 | D13: 9779 | E13: 1137 | F13: 10210 | G13: 8249 | H13: 4944 | I13: 3095 | J13: 3198 | K13: 5870 | L13: 10446 | M13: 9262
A14: Total Opex | B14: =SUM(B5:B13) -> 67148 | C14: =SUM(C5:C13) -> 53734 | D14: =SUM(D5:D13) -> 71785 | E14: =SUM(E5:E13) -> 62598 | F14: =SUM(F5:F13) -> 52466 | G14: =SUM(G5:G13) -> 56426 | H14: =SUM(H5:H13) -> 63017 | I14: =SUM(I5:I13) -> 58499 | ... M14: =SUM(M5:M13) -> 53090
A15: Operating Profit | B15: =B4-B14 -> -26432 | C15: =C4-C14 -> 44885 | D15: =D4-D14 -> 19333 | E15: =E4-E14 -> 22054 | F15: =F4-F14 -> -5922 | G15: =G4-G14 -> 18885 | H15: =H4-H14 -> 11686 | I15: =I4-I14 -> 14706 | ... M15: =M4-M14 -> -602
A16: Margin | B16: =B15/B2 -> -0.30512075 | C16: =C15/C2 -> 0.23212097 | D16: =D15/D2 -> 0.10396657 | E16: =E15/E2 -> 0.11463174 | F16: =F15/F2 -> -0.069980147 | G16: =G15/G2 -> 0.1278891 | H16: =H15/H2 -> 0.075088351 | I16: =I15/I2 -> 0.11651639 | ... M16: =M15/M2 -> -0.0053906425

Sheet Branch5
A1: Account | B1: Jan | C1: Feb | D1: Mar | E1: Apr | F1: May | G1: Jun | H1: Jul | I1: Aug | J1: Sep | K1: Oct | L1: Nov | M1: Dec
A2: Revenue | B2: 169936 | C2: 120194 | D2: 127907 | E2: 140381 | F2: 82772 | G2: 191138 | H2: 114368 | I2: 179015 | J2: 174910 | K2: 112351 | L2: 81823 | M2: 194547
A3: COGS | B3: 71373 | C3: 56491 | D3: 71627 | E3: 57556 | F3: 49663 | G3: 87923 | H3: 52609 | I3: 91297 | J3: 73462 | K3: 55051 | L3: 36002 | M3: 87546
A4: Gross Profit | B4: =B2-B3 -> 98563 | C4: =C2-C3 -> 63703 | D4: =D2-D3 -> 56280 | E4: =E2-E3 -> 82825 | F4: =F2-F3 -> 33109 | G4: =G2-G3 -> 103215 | H4: =H2-H3 -> 61759 | I4: =I2-I3 -> 87718 | ... M4: =M2-M3 -> 107001
A5: Salaries | B5: 6097 | C5: 10550 | D5: 6017 | E5: 6681 | F5: 10891 | G5: 10349 | H5: 2390 | I5: 5855 | J5: 4210 | K5: 6265 | L5: 1078 | M5: 10435
A6: Rent | B6: 1229 | C6: 2439 | D6: 8568 | E6: 8793 | F6: 6478 | G6: 9549 | H6: 10327 | I6: 2233 | J6: 8627 | K6: 4027 | L6: 8036 | M6: 3063
A7: Utilities | B7: 11311 | C7: 10438 | D7: 11484 | E7: 1859 | F7: 5980 | G7: 5220 | H7: 2561 | I7: 3237 | J7: 4183 | K7: 6868 | L7: 1674 | M7: 7644
A8: Marketing | B8: 6618 | C8: 5207 | D8: 11941 | E8: 7024 | F8: 2325 | G8: 10195 | H8: 5371 | I8: 9431 | J8: 1759 | K8: 8479 | L8: 11667 | M8: 3443
A9: Insurance | B9: 5083 | C9: 4958 | D9: 11351 | E9: 11344 | F9: 10815 | G9: 8326 | H9: 5684 | I9: 3826 | J9: 9258 | K9: 2097 | L9: 4293 | M9: 4347
A10: Depreciation | B10: 8645 | C10: 8114 | D10: 9448 | E10: 6186 | F10: 6594 | G10: 6971 | H10: 9075 | I10: 8149 | J10: 4500 | K10: 2417 | L10: 11999 | M10: 2428
A11: Travel | B11: 3672 | C11: 6562 | D11: 5748 | E11: 11685 | F11: 9485 | G11: 7842 | H11: 2423 | I11: 11988 | J11: 8784 | K11: 11838 | L11: 3263 | M11: 10406
A12: Supplies | B12: 7632 | C12: 11677 | D12: 6895 | E12: 11447 | F12: 8222 | G12: 5017 | H12: 2175 | I12: 2703 | J12: 6861 | K12: 9736 | L12: 5449 | M12: 10188
A13: Maintenance | B13: 6142 | C13: 11681 | D13: 3905 | E13: 10320 | F13: 11752 | G13: 1277 | H13: 5063 | I13: 9563 | J13: 6694 | K13: 10208 | L13: 5034 | M13: 9162
A14: Total Opex | B14: =SUM(B5:B13) -> 56429 | C14: =SUM(C5:C13) -> 71626 | D14: =SUM(D5:D13) -> 75357 | E14: =SUM(E5:E13) -> 75339 | F14: =SUM(F5:F13) -> 72542 | G14: =SUM(G5:G13) -> 64746 | H14: =SUM(H5:H13) -> 45069 | I14: =SUM(I5:I13) -> 56985 | ... M14: =SUM(M5:M13) -> 61116
A15: Operating Profit | B15: =B4-B14 -> 42134 | C15: =C4-C14 -> -7923 | D15: =D4-D14 -> -19077 | E15: =E4-E14 -> 7486 | F15: =F4-F14 -> -39433 | G15: =G4-G14 -> 38469 | H15: =H4-H14 -> 16690 | I15: =I4-I14 -> 30733 | ... M15: =M4-M14 -> 45885
A16: Margin | B16: =B15/B2 -> 0.2479404 | C16: =C15/C2 -> -0.065918432 | D16: =D15/D2 -> -0.14914743 | E16: =E15/E2 -> 0.053326305 | F16: =F15/F2 -> -0.47640506 | G16: =G15/G2 -> 0.20126296 | H16: =H15/H2 -> 0.14593243 | I16: =I15/I2 -> 0.17167835 | ... M16: =M15/M2 -> 0.2358556

Sheet Consolidated
A1: Account | B1: Jan | C1: Feb | D1: Mar | E1: Apr | F1: May | G1: Jun | H1: Jul | I1: Aug | J1: Sep | K1: Oct | L1: Nov | M1: Dec
A2: Revenue | B2: =SUM(Branch1!B2,Branch2!B2,Branch3!B2,Branch4!B2,Branch5!B2) -> 742288 | C2: =SUM(Branch1!C2,Branch2!C2,Branch3!C2,Branch4!C2,Branch5!C2) -> 804375 | D2: =SUM(Branch1!D2,Branch2!D2,Branch3!D2,Branch4!D2,Branch5!D2) -> 801494 | E2: =SUM(Branch1!E2,Branch2!E2,Branch3!E2,Branch4!E2,Branch5!E2) -> 764685 | F2: =SUM(Branch1!F2,Branch2!F2,Branch3!F2,Branch4!F2,Branch5!F2) -> 530943 | G2: =SUM(Branch1!G2,Branch2!G2,Branch3!G2,Branch4!G2,Branch5!G2) -> 873334 | H2: =SUM(Branch1!H2,Branch2!H2,Branch3!H2,Branch4!H2,Branch5!H2) -> 471538 | I2: =SUM(Branch1!I2,Branch2!I2,Branch3!I2,Branch4!I2,Branch5!I2) -> 655770 | ... M2: =SUM(Branch1!M2,Branch2!M2,Branch3!M2,Branch4!M2,Branch5!M2) -> 667774
A3: COGS | B3: =SUM(Branch1!B3,Branch2!B3,Branch3!B3,Branch4!B3,Branch5!B3) -> 366379 | C3: =SUM(Branch1!C3,Branch2!C3,Branch3!C3,Branch4!C3,Branch5!C3) -> 408262 | D3: =SUM(Branch1!D3,Branch2!D3,Branch3!D3,Branch4!D3,Branch5!D3) -> 438102 | E3: =SUM(Branch1!E3,Branch2!E3,Branch3!E3,Branch4!E3,Branch5!E3) -> 375461 | F3: =SUM(Branch1!F3,Branch2!F3,Branch3!F3,Branch4!F3,Branch5!F3) -> 263994 | G3: =SUM(Branch1!G3,Branch2!G3,Branch3!G3,Branch4!G3,Branch5!G3) -> 417780 | H3: =SUM(Branch1!H3,Branch2!H3,Branch3!H3,Branch4!H3,Branch5!H3) -> 234345 | I3: =SUM(Branch1!I3,Branch2!I3,Branch3!I3,Branch4!I3,Branch5!I3) -> 322289 | ... M3: =SUM(Branch1!M3,Branch2!M3,Branch3!M3,Branch4!M3,Branch5!M3) -> 341409
A4: Gross Profit | B4: =B2-B3 -> 375909 | C4: =C2-C3 -> 396113 | D4: =D2-D3 -> 363392 | E4: =E2-E3 -> 389224 | F4: =F2-F3 -> 266949 | G4: =G2-G3 -> 455554 | H4: =H2-H3 -> 237193 | I4: =I2-I3 -> 333481 | ... M4: =M2-M3 -> 326365
A5: Salaries | B5: =SUM(Branch1!B5,Branch2!B5,Branch3!B5,Branch4!B5,Branch5!B5) -> 30210 | C5: =SUM(Branch1!C5,Branch2!C5,Branch3!C5,Branch4!C5,Branch5!C5) -> 45426 | D5: =SUM(Branch1!D5,Branch2!D5,Branch3!D5,Branch4!D5,Branch5!D5) -> 28252 | E5: 54321 | F5: =SUM(Branch1!F5,Branch2!F5,Branch3!F5,Branch4!F5,Branch5!F5) -> 38573 | G5: =SUM(Branch1!G5,Branch2!G5,Branch3!G5,Branch4!G5,Branch5!G5) -> 34749 | H5: =SUM(Branch1!H5,Branch2!H5,Branch3!H5,Branch4!H5,Branch5!H5) -> 32266 | I5: =SUM(Branch1!I5,Branch2!I5,Branch3!I5,Branch4!I5,Branch5!I5) -> 36367 | J5: =SUM(Branch1!J5,Branch2!J5,Branch3!J5,Branch4!J5,Branch5!J5) -> 21332 | K5: =SUM(Branch1!K5,Branch2!K5,Branch3!K5,Branch4!K5,Branch5!K5) -> 19898 | L5: =SUM(Branch1!L5,Branch2!L5,Branch3!L5,Branch4!L5,Branch5!L5) -> 19109 | M5: =SUM(Branch1!M5,Branch2!M5,Branch3!M5,Branch4!M5,Branch5!M5) -> 31385
A6: Rent | B6: =SUM(Branch1!B6,Branch2!B6,Branch3!B6,Branch4!B6,Branch5!B6) -> 30115 | C6: =SUM(Branch1!C6,Branch2!C6,Branch3!C6,Branch4!C6,Branch5!C6) -> 26153 | D6: =SUM(Branch1!D6,Branch2!D6,Branch3!D6,Branch4!D6,Branch5!D6) -> 29356 | E6: =SUM(Branch1!E6,Branch2!E6,Branch3!E6,Branch4!E6,Branch5!E6) -> 37612 | F6: =SUM(Branch1!F6,Branch2!F6,Branch3!F6,Branch4!F6,Branch5!F6) -> 31091 | G6: =SUM(Branch1!G6,Branch2!G6,Branch3!G6,Branch4!G6,Branch5!G6) -> 28929 | H6: =SUM(Branch1!H6,Branch2!H6,Branch3!H6,Branch4!H6,Branch5!H6) -> 46116 | I6: =SUM(Branch1!I6,Branch2!I6,Branch3!I6,Branch4!I6,Branch5!I6) -> 24044 | ... M6: =SUM(Branch1!M6,Branch2!M6,Branch3!M6,Branch4!M6,Branch5!M6) -> 25627
A7: Utilities | B7: =SUM(Branch1!B7,Branch2!B7,Branch3!B7,Branch4!B7,Branch5!B7) -> 40042 | C7: =SUM(Branch1!C7,Branch2!C7,Branch3!C7,Branch4!C7,Branch5!C7) -> 44607 | D7: =SUM(Branch1!D7,Branch2!D7,Branch3!D7,Branch4!D7,Branch5!D7) -> 48697 | E7: =SUM(Branch1!E7,Branch2!E7,Branch3!E7,Branch4!E7,Branch5!E7) -> 33533 | F7: =SUM(Branch1!F7,Branch2!F7,Branch3!F7,Branch4!F7,Branch5!F7) -> 17332 | G7: =SUM(Branch1!G7,Branch2!G7,Branch3!G7,Branch4!G7,Branch5!G7) -> 30622 | H7: =SUM(Branch1!H7,Branch2!H7,Branch3!H7,Branch4!H7,Branch5!H7) -> 33974 | I7: =SUM(Branch1!I7,Branch2!I7,Branch3!I7,Branch4!I7,Branch5!I7) -> 38413 | ... M7: =SUM(Branch1!M7,Branch2!M7,Branch3!M7,Branch4!M7,Branch5!M7) -> 22113
A8: Marketing | B8: =SUM(Branch1!B8,Branch2!B8,Branch3!B8,Branch4!B8,Branch5!B8) -> 24767 | C8: =SUM(Branch1!C8,Branch2!C8,Branch3!C8,Branch4!C8,Branch5!C8) -> 38738 | D8: =SUM(Branch1!D8,Branch2!D8,Branch3!D8,Branch4!D8,Branch5!D8) -> 40054 | E8: =SUM(Branch1!E8,Branch2!E8,Branch3!E8,Branch4!E8,Branch5!E8) -> 33772 | F8: =SUM(Branch1!F8,Branch2!F8,Branch3!F8,Branch4!F8,Branch5!F8) -> 24836 | G8: =SUM(Branch1!G8,Branch2!G8,Branch3!G8,Branch4!G8,Branch5!G8) -> 26212 | H8: =SUM(Branch1!H8,Branch2!H8,Branch3!H8,Branch4!H8,Branch5!H8) -> 32553 | I8: =SUM(Branch1!I8,Branch2!I8,Branch3!I8,Branch4!I8,Branch5!I8) -> 42635 | ... M8: =SUM(Branch1!M8,Branch2!M8,Branch3!M8,Branch4!M8,Branch5!M8) -> 31599
A9: Insurance | B9: =SUM(Branch1!B9,Branch2!B9,Branch3!B9,Branch4!B9,Branch5!B9) -> 38502 | C9: =SUM(Branch1!C9,Branch2!C9,Branch3!C9,Branch4!C9,Branch5!C9) -> 39728 | D9: =SUM(Branch1!D9,Branch2!D9,Branch3!D9,Branch4!D9,Branch5!D9) -> 44896 | E9: =SUM(Branch1!E9,Branch2!E9,Branch3!E9,Branch4!E9,Branch5!E9) -> 34454 | F9: =SUM(Branch1!F9,Branch2!F9,Branch3!F9,Branch4!F9,Branch5!F9) -> 40316 | G9: =SUM(Branch1!G9,Branch2!G9,Branch3!G9,Branch4!G9,Branch5!G9) -> 29102 | H9: =SUM(Branch1!H9,Branch2!H9,Branch3!H9,Branch4!H9,Branch5!H9) -> 31573 | I9: =SUM(Branch1!I9,Branch2!I9,Branch3!I9,Branch4!I9,Branch5!I9) -> 22911 | ... M9: =SUM(Branch1!M9,Branch2!M9,Branch3!M9,Branch4!M9,Branch5!M9) -> 33265
A10: Depreciation | B10: =SUM(Branch1!B10,Branch2!B10,Branch3!B10,Branch4!B10,Branch5!B10) -> 34488 | C10: =SUM(Branch1!C10,Branch2!C10,Branch3!C10,Branch4!C10,Branch5!C10) -> 44614 | D10: =SUM(Branch1!D10,Branch2!D10,Branch3!D10,Branch4!D10,Branch5!D10) -> 42655 | E10: =SUM(Branch1!E10,Branch2!E10,Branch3!E10,Branch4!E10,Branch5!E10) -> 36824 | F10: =SUM(Branch1!F10,Branch2!F10,Branch3!F10,Branch4!F10,Branch5!F10) -> 30218 | G10: =SUM(Branch1!G10,Branch2!G10,Branch3!G10,Branch4!G10,Branch5!G10) -> 28672 | H10: =SUM(Branch1!H10,Branch2!H10,Branch3!H10,Branch4!H10,Branch5!H10) -> 19246 | I10: =SUM(Branch1!I10,Branch2!I10,Branch3!I10,Branch4!I10,Branch5!I10) -> 32067 | ... M10: =SUM(Branch1!M10,Branch2!M10,Branch3!M10,Branch4!M10,Branch5!M10) -> 23714
A11: Travel | B11: =SUM(Branch1!B11,Branch2!B11,Branch3!B11,Branch4!B11,Branch5!B11) -> 34841 | C11: =SUM(Branch1!C11,Branch2!C11,Branch3!C11,Branch4!C11,Branch5!C11) -> 35340 | D11: =SUM(Branch1!D11,Branch2!D11,Branch3!D11,Branch4!D11,Branch5!D11) -> 30439 | E11: =SUM(Branch1!E11,Branch2!E11,Branch3!E11,Branch4!E11,Branch5!E11) -> 34735 | F11: =SUM(Branch1!F11,Branch2!F11,Branch3!F11,Branch4!F11,Branch5!F11) -> 32923 | G11: =SUM(Branch1!G11,Branch2!G11,Branch3!G11,Branch4!G11,Branch5!G11) -> 33885 | H11: =SUM(Branch1!H11,Branch2!H11,Branch3!H11,Branch4!H11,Branch5!H11) -> 23034 | I11: =SUM(Branch1!I11,Branch2!I11,Branch3!I11,Branch4!I11,Branch5!I11) -> 54941 | ... M11: =SUM(Branch1!M11,Branch2!M11,Branch3!M11,Branch4!M11,Branch5!M11) -> 42285
A12: Supplies | B12: =SUM(Branch1!B12,Branch2!B12,Branch3!B12,Branch4!B12,Branch5!B12) -> 24292 | C12: =SUM(Branch1!C12,Branch2!C12,Branch3!C12,Branch4!C12,Branch5!C12) -> 41018 | D12: =SUM(Branch1!D12,Branch2!D12,Branch3!D12,Branch4!D12,Branch5!D12) -> 39140 | E12: =SUM(Branch1!E12,Branch2!E12,Branch3!E12,Branch4!E12,Branch5!E12) -> 29740 | F12: =SUM(Branch1!F12,Branch2!F12,Branch3!F12,Branch4!F12,Branch5!F12) -> 39518 | G12: =SUM(Branch1!G12,Branch2!G12,Branch3!G12,Branch4!G12,Branch5!G12) -> 32936 | H12: =SUM(Branch1!H12,Branch2!H12,Branch3!H12,Branch4!H12,Branch5!H12) -> 33762 | I12: =SUM(Branch1!I12,Branch2!I12,Branch3!I12,Branch4!I12,Branch5!I12) -> 36349 | ... M12: =SUM(Branch1!M12,Branch2!M12,Branch3!M12,Branch4!M12,Branch5!M12) -> 40831
A13: Maintenance | B13: =SUM(Branch1!B13,Branch2!B13,Branch3!B13,Branch4!B13,Branch5!B13) -> 42364 | C13: =SUM(Branch1!C13,Branch2!C13,Branch3!C13,Branch4!C13,Branch5!C13) -> 37070 | D13: =SUM(Branch1!D13,Branch2!D13,Branch3!D13,Branch4!D13,Branch5!D13) -> 34589 | E13: =SUM(Branch1!E13,Branch2!E13,Branch3!E13,Branch4!E13,Branch5!E13) -> 38838 | F13: =SUM(Branch1!F13,Branch2!F13,Branch3!F13,Branch4!F13,Branch5!F13) -> 34916 | G13: =SUM(Branch1!G13,Branch2!G13,Branch3!G13,Branch4!G13,Branch5!G13) -> 18308 | H13: =SUM(Branch1!H13,Branch2!H13,Branch3!H13,Branch4!H13,Branch5!H13) -> 22603 | I13: =SUM(Branch1!I13,Branch2!I13,Branch3!I13,Branch4!I13,Branch5!I13) -> 30811 | ... M13: =SUM(Branch1!M13,Branch2!M13,Branch3!M13,Branch4!M13,Branch5!M13) -> 41279
A14: Total Opex | B14: =SUM(B5:B13) -> 299621 | C14: =SUM(C5:C13) -> 352694 | D14: =SUM(D5:D13) -> 338078 | E14: =SUM(E5:E13) -> 333829 | F14: =SUM(F5:F13) -> 289723 | G14: =SUM(G5:G13) -> 263415 | H14: =SUM(H5:H13) -> 275127 | I14: =SUM(I5:I13) -> 318538 | ... M14: =SUM(M5:M13) -> 292098
A15: Operating Profit | B15: =B4-B14 -> 76288 | C15: =C4-C14 -> 43419 | D15: =D4-D14 -> 25314 | E15: =E4-E14 -> 55395 | F15: =F4-F14 -> -22774 | G15: =G4-G14 -> 192139 | H15: =H4-H14 -> -37934 | I15: =I4-I14 -> 14943 | ... M15: =M4-M14 -> 34267
A16: Margin | B16: =B15/B2 -> 0.10277413 | C16: =C15/C2 -> 0.053978555 | D16: =D15/D2 -> 0.031583518 | E16: =E15/E2 -> 0.072441594 | F16: =F15/F2 -> -0.042893493 | G16: =G15/G2 -> 0.22000632 | H16: =H15/H2 -> -0.080447387 | I16: =I15/I2 -> 0.022786953 | ... M16: =M15/M2 -> 0.051315265
A18: Net Cash | B18: =B15+B10 -> 110776 | C18: =C15+C10 -> 88033 | D18: =D15+D10 -> 67969 | E18: =E15+E10 -> 92219 | F18: =F15+F10 -> 7444 | G18: =G15+G10 -> 220811 | H18: =H15+H10 -> -18688 | I18: =I15+I10 -> 47010 | ... M18: =M15+M10 -> 57981
A19: Cumulative Cash | B19: =B18 -> 110776 | C19: =B19+C18 -> 198809 | D19: =C19+D18 -> 266778 | E19: =D19+E18 -> 358997 | F19: =E19+F18 -> 366441 | G19: =F19+G18 -> 587252 | H19: =G19+H18 -> 568564 | I19: =H19+I18 -> 615574 | J19: =I19+J18 -> 803944 | ... M19: =L19+M18 -> 1000629
